maxpool2d.sv
module max_pool2d #(
    parameter int in_width  = 28,
    parameter int out_width = 14
)(
    input  logic        reset,
    input  logic clk,
    input  logic signed [in_width*in_width*32-1:0]   in_map,
    output logic signed [out_width*out_width*32-1:0] out_map,
    output logic done
);
    int unsigned out_y = 0;
    int unsigned out_x = 0;

    logic signed [31:0] max_val;
    logic signed [31:0] curr_val;

    always_comb begin

        max_val = in_map[((2*out_y)*in_width + (2*out_x))*32 +: 32];

        for (int ky = 0; ky < 2; ky++) begin
            for (int kx = 0; kx < 2; kx++) begin
               if ((2*out_y + ky) < in_width && (2*out_x + kx) < in_width) begin
                curr_val = in_map[((2*out_y + ky)*in_width + (2*out_x + kx))*32 +: 32];
                end else begin
                curr_val = 32'd0; 
            end 
                if ($signed(curr_val) > $signed(max_val)) max_val = curr_val;
            end
        end
    end


    always_ff @(posedge clk) begin
        if (reset) begin
            out_x <= 0;
            out_y <= 0;
            done <= 0;
        end else if (done == 0 && out_y == out_width - 1 && out_x == out_width - 1) begin
            done <= 1;
        end else if (out_x == out_width - 1) begin
            out_x <= 0;
            if (out_y == out_width - 1) out_y <= 0;
            else                        out_y <= out_y + 1;
        end else begin
            out_x <= out_x + 1;
        end
        out_map[(out_y*out_width + out_x)*32 +: 32] <= max_val;

    end

endmodule

relu.sv
module relu #(
    parameter int map_width
)
(
    input logic clk,
    input logic reset,
    input logic signed [map_width*map_width*32-1:0] input_map,
    output logic signed [map_width*map_width*32-1:0] output_map,
    output logic done
);

int x = 0;
int y = 0;
int idx;
initial begin
done = 0;
end
always_ff @(posedge clk) begin
    if (reset) begin
        x <= 0;
        y <= 0;
        done <= 0;
    end else

    if (!done) begin
        idx <= (x*map_width + y) * 32; 
        output_map[idx +:32] <= 
            ($signed(input_map[idx +:32]) > 0) ? input_map[idx +:32] : 32'd0;
        if (x==map_width && y==map_width) begin
            done <= 1;
        end else if (x == map_width-1 && y == map_width-1) begin
            x <= 0;
            y <= 0;
        end else if (y == map_width-1) begin
            y <= 0;
            x <= x+1;
        end else begin
            y <= y+1;
        end
    end

end


endmodule

conv2d.sv
module conv2d #(
    parameter int kernel_size,
    parameter int stride,
    parameter int input_width,
    parameter int output_width
)(
    input  logic clk,
    input  logic reset,
    input  logic [kernel_size*kernel_size-1:0] filter,
    input  logic signed [input_width*input_width*32-1:0]    input_image,
    output logic signed [output_width*output_width*32-1:0]  output_image,
    output logic done
);

    int output_x = 0;
    int output_y = 0;

    logic signed [63:0] kernel_sum;
    logic signed [63:0] weighted_val;

    int base_x;
    int base_y;

    int input_x;
    int input_y;

    always_comb begin
        kernel_sum = 64'b0;

        base_x = output_x * stride;
        base_y = output_y * stride;

        for (int ky = 0; ky < kernel_size; ky++) begin
            for (int kx = 0; kx < kernel_size; kx++) begin

                int input_x = base_x + kx;
                int input_y = base_y + ky;

                if (input_x < 0 || input_x >= input_width || input_y < 0 || input_y >= input_width) begin
                    weighted_val = 64'b0;
                end else begin
                    weighted_val = input_image[(input_y*input_width + input_x)*32 +: 32] * filter[(ky*kernel_size) + kx];
                end

                kernel_sum += weighted_val;
            end
        end
    end

    always_ff @(posedge clk) begin
        if (reset) begin
            output_x <= 0;
            output_y <= 0;
            done     <= 0;
        end else begin

            if (!done) begin
                output_image[(output_y*output_width + output_x)*32 +: 32] <= kernel_sum[31:0];

                if (output_x == output_width-1) begin
                    output_x <= 0;
                    if (output_y == output_width-1) begin
                        output_y <= 0;
                        done <= 1;
                    end else begin
                        output_y <= output_y + 1;
                    end
                end else begin
                    output_x <= output_x + 1;
                end
            end

        end
    end

endmodule

memory.sv
module memory #(
    parameter string INIT_FILE = "",
    parameter int image_width = 28
)(
    output logic signed [image_width*image_width*32-1:0] read_data
);

    // Make the stored bytes signed (-128..127 or -127..127 depending on your file)
    logic signed [7:0] mem [0:2047];

    initial begin
        if (INIT_FILE != "") begin
            $readmemh(INIT_FILE, mem);

            for (int i = 0; i < image_width*image_width; i++) begin
                // Sign-extend 8 -> 32
                read_data[i*32 +: 32] = $signed(mem[i]);
            end
        end
    end

endmodule

top.sv
`include "memory.sv"
`include "conv2d.sv"
`include "relu.sv"
`include "maxpool2d.sv"

module top #(
    parameter image_width = 5,
    parameter pooled_width = 3,
    parameter kernel_width = 3,
    parameter stride = 2,
    parameter filtered_width = 2
)(
    input logic clk
);
    logic relu_reset = 0;
    logic max_pool_reset = 0;
    logic conv_reset = 0;

    logic signed[image_width*image_width*32-1:0] input_image;
    
    logic relu_done;
    logic max_pool_done;
    logic conv_done;

    logic signed [filtered_width*filtered_width*32-1:0] filtered_output;
    logic [image_width*image_width*32-1:0] relu_output;
    logic signed [pooled_width*pooled_width*32-1:0] pooled_output;

    logic [kernel_width*kernel_width-1:0] filter;

    initial begin
        filter = 9'b101010101;
    end

    memory #(
        .INIT_FILE      ("zero_padding.txt"),
        .image_width    (image_width)
    ) u1 (
        .read_data      (input_image)
    );
    conv2d #(
        .kernel_size    (kernel_width),
        .stride         (stride),
        .input_width    (image_width),
        .output_width   (filtered_width)
    ) conv2d (
        .clk            (clk),
        .reset          (conv_reset),
        .filter         (filter),
        .input_image    (input_image),
        .output_image   (filtered_output),
        .done           (conv_done)
    );
    relu #(
        .map_width       (image_width)
    ) relu (
        .reset           (relu_reset),
        .clk             (clk),
        .input_map       (input_image),
        .output_map      (relu_output),
        .done            (relu_done)
    );
    max_pool2d #(
        .in_width(image_width),
        .out_width(pooled_width)
    ) maxpool2d (
        .clk(clk),
        .reset(max_pool_reset),
        .in_map(input_image),
        .out_map(pooled_output),
        .done (max_pool_done)
    );


endmodule

top_tb.sv
`timescale 10ns/10ns
`include "top.sv"

module ai_fpga_tb;

    logic clk = 0;
    top u0 (
        .clk            (clk)
    );

    initial begin
        $dumpfile("top_tb.vcd");
        $dumpvars(0, ai_fpga_tb);
        #100000
        $finish;
    end

    always begin
        #4
        clk = ~clk;
    end

endmodule

top_tb.vcd
$date
	Tue Dec 16 18:43:55 2025
$end
$version
	Icarus Verilog
$end
$timescale
	10ns
$end
$scope module ai_fpga_tb $end
$var reg 1 ! clk $end
$scope module u0 $end
$var wire 1 ! clk $end
$var wire 800 " relu_output [799:0] $end
$var wire 1 # relu_done $end
$var wire 288 $ pooled_output [287:0] $end
$var wire 1 % max_pool_done $end
$var wire 800 & input_image [799:0] $end
$var wire 128 ' filtered_output [127:0] $end
$var wire 1 ( conv_done $end
$var parameter 32 ) filtered_width $end
$var parameter 32 * image_width $end
$var parameter 32 + kernel_width $end
$var parameter 32 , pooled_width $end
$var parameter 32 - stride $end
$var reg 1 . conv_reset $end
$var reg 9 / filter [8:0] $end
$var reg 1 0 max_pool_reset $end
$var reg 1 1 relu_reset $end
$scope module conv2d $end
$var wire 1 ! clk $end
$var wire 9 2 filter [8:0] $end
$var wire 1 . reset $end
$var wire 800 3 input_image [799:0] $end
$var parameter 32 4 input_width $end
$var parameter 32 5 kernel_size $end
$var parameter 32 6 output_width $end
$var parameter 32 7 stride $end
$var reg 1 ( done $end
$var reg 64 8 kernel_sum [63:0] $end
$var reg 128 9 output_image [127:0] $end
$var reg 64 : weighted_val [63:0] $end
$var integer 32 ; base_x [31:0] $end
$var integer 32 < base_y [31:0] $end
$var integer 32 = output_x [31:0] $end
$var integer 32 > output_y [31:0] $end
$scope begin $ivl_for_loop1 $end
$var integer 32 ? ky [31:0] $end
$scope begin $ivl_for_loop2 $end
$var integer 32 @ kx [31:0] $end
$scope begin $unm_blk_6 $end
$var integer 32 A input_x [31:0] $end
$var integer 32 B input_y [31:0] $end
$upscope $end
$upscope $end
$upscope $end
$upscope $end
$scope module maxpool2d $end
$var wire 1 ! clk $end
$var wire 1 0 reset $end
$var wire 800 C in_map [799:0] $end
$var parameter 32 D in_width $end
$var parameter 32 E out_width $end
$var reg 32 F curr_val [31:0] $end
$var reg 1 % done $end
$var reg 32 G max_val [31:0] $end
$var reg 288 H out_map [287:0] $end
$var reg 32 I out_x [31:0] $end
$var reg 32 J out_y [31:0] $end
$scope begin $ivl_for_loop3 $end
$var integer 32 K ky [31:0] $end
$scope begin $ivl_for_loop4 $end
$var integer 32 L kx [31:0] $end
$upscope $end
$upscope $end
$upscope $end
$scope module relu $end
$var wire 1 ! clk $end
$var wire 1 1 reset $end
$var wire 800 M input_map [799:0] $end
$var parameter 32 N map_width $end
$var reg 1 # done $end
$var reg 800 O output_map [799:0] $end
$var integer 32 P idx [31:0] $end
$var integer 32 Q x [31:0] $end
$var integer 32 R y [31:0] $end
$upscope $end
$scope module u1 $end
$var parameter 128 S INIT_FILE $end
$var parameter 32 T image_width $end
$var reg 800 U read_data [799:0] $end
$scope begin $ivl_for_loop0 $end
$var integer 32 V i [31:0] $end
$upscope $end
$upscope $end
$upscope $end
$upscope $end
$enddefinitions $end
$comment Show the parameter values. $end
$dumpall
b101 T
b1111010011001010111001001101111010111110111000001100001011001000110010001101001011011100110011100101110011101000111100001110100 S
b101 N
b11 E
b101 D
b10 7
b10 6
b11 5
b101 4
b10 -
b11 ,
b11 +
b101 *
b10 )
$end
#0
$dumpvars
b11001 V
b11111111111111111111111110000001111111111111111111111111100000011111111111111111111111111000000111111111111111111111111110000001111111111111111111111111100000011111111111111111111111111000000100000000000000000000000001111111000000000000000000000000011111110000000000000000000000000111111111111111111111111111111110000001111111111111111111111111100000010000000000000000000000000111111100000000000000000000000001111111000000000000000000000000011111111111111111111111111111111000000100000000000000000000000001111111000000000000000000000000011111110000000000000000000000000111111100000000000000000000000001111111111111111111111111111111100000011111111111111111111111111000000100000000000000000000000001111111000000000000000000000000011111110000000000000000000000000111111111111111111111111111111110000001 U
b0 R
b0 Q
b0 P
bx O
b11111111111111111111111110000001111111111111111111111111100000011111111111111111111111111000000111111111111111111111111110000001111111111111111111111111100000011111111111111111111111111000000100000000000000000000000001111111000000000000000000000000011111110000000000000000000000000111111111111111111111111111111110000001111111111111111111111111100000010000000000000000000000000111111100000000000000000000000001111111000000000000000000000000011111111111111111111111111111111000000100000000000000000000000001111111000000000000000000000000011111110000000000000000000000000111111100000000000000000000000001111111111111111111111111111111100000011111111111111111111111111000000100000000000000000000000001111111000000000000000000000000011111110000000000000000000000000111111111111111111111111111111110000001 M
b10 L
b10 K
b0 J
b0 I
bx H
b1111111 G
b1111111 F
b11111111111111111111111110000001111111111111111111111111100000011111111111111111111111111000000111111111111111111111111110000001111111111111111111111111100000011111111111111111111111111000000100000000000000000000000001111111000000000000000000000000011111110000000000000000000000000111111111111111111111111111111110000001111111111111111111111111100000010000000000000000000000000111111100000000000000000000000001111111000000000000000000000000011111111111111111111111111111111000000100000000000000000000000001111111000000000000000000000000011111110000000000000000000000000111111100000000000000000000000001111111111111111111111111111111100000011111111111111111111111111000000100000000000000000000000001111111000000000000000000000000011111110000000000000000000000000111111111111111111111111111111110000001 C
b0 B
b0 A
b11 @
b11 ?
b0 >
b0 =
b0 <
b0 ;
b11111111111111111111111110000001 :
bx 9
b10011111111111111111111110110000101 8
b11111111111111111111111110000001111111111111111111111111100000011111111111111111111111111000000111111111111111111111111110000001111111111111111111111111100000011111111111111111111111111000000100000000000000000000000001111111000000000000000000000000011111110000000000000000000000000111111111111111111111111111111110000001111111111111111111111111100000010000000000000000000000000111111100000000000000000000000001111111000000000000000000000000011111111111111111111111111111111000000100000000000000000000000001111111000000000000000000000000011111110000000000000000000000000111111100000000000000000000000001111111111111111111111111111111100000011111111111111111111111111000000100000000000000000000000001111111000000000000000000000000011111110000000000000000000000000111111111111111111111111111111110000001 3
b101010101 2
01
00
b101010101 /
0.
x(
bx '
b11111111111111111111111110000001111111111111111111111111100000011111111111111111111111111000000111111111111111111111111110000001111111111111111111111111100000011111111111111111111111111000000100000000000000000000000001111111000000000000000000000000011111110000000000000000000000000111111111111111111111111111111110000001111111111111111111111111100000010000000000000000000000000111111100000000000000000000000001111111000000000000000000000000011111111111111111111111111111111000000100000000000000000000000001111111000000000000000000000000011111110000000000000000000000000111111100000000000000000000000001111111111111111111111111111111100000011111111111111111111111111000000100000000000000000000000001111111000000000000000000000000011111110000000000000000000000000111111111111111111111111111111110000001 &
x%
bx $
0#
bx "
0!
$end
#4
b10 L
b10 K
b1 R
bx00000000000000000000000000000000 "
bx00000000000000000000000000000000 O
bx00000000000000000000000001111111 $
bx00000000000000000000000001111111 H
b1 I
1!
#8
0!
#12
b0 F
b10 L
b10 K
b1111111 G
bx0000000000000000000000000111111100000000000000000000000001111111 $
bx0000000000000000000000000111111100000000000000000000000001111111 H
b10 I
b10 R
b100000 P
1!
#16
0!
#20
b1111111 F
b10 L
b10 K
b1111111 G
b11 R
bx0000000000000000000000000111111100000000000000000000000000000000 "
bx0000000000000000000000000111111100000000000000000000000000000000 O
b1000000 P
bx000000000000000000000000011111110000000000000000000000000111111100000000000000000000000001111111 $
bx000000000000000000000000011111110000000000000000000000000111111100000000000000000000000001111111 H
b1 J
b0 I
1!
#24
0!
#28
b10 L
b10 K
bx00000000000000000000000001111111000000000000000000000000011111110000000000000000000000000111111100000000000000000000000001111111 $
bx00000000000000000000000001111111000000000000000000000000011111110000000000000000000000000111111100000000000000000000000001111111 H
b1 I
b100 R
bx000000000000000000000000011111110000000000000000000000000111111100000000000000000000000000000000 "
bx000000000000000000000000011111110000000000000000000000000111111100000000000000000000000000000000 O
b1100000 P
1!
#32
0!
#36
b0 F
b10 L
b10 K
b0 G
b1 Q
b0 R
bx00000000000000000000000001111111000000000000000000000000011111110000000000000000000000000111111100000000000000000000000000000000 "
bx00000000000000000000000001111111000000000000000000000000011111110000000000000000000000000111111100000000000000000000000000000000 O
b10000000 P
bx0000000000000000000000000111111100000000000000000000000001111111000000000000000000000000011111110000000000000000000000000111111100000000000000000000000001111111 $
bx0000000000000000000000000111111100000000000000000000000001111111000000000000000000000000011111110000000000000000000000000111111100000000000000000000000001111111 H
b10 I
1!
#40
0!
#44
b0 F
b10 L
b10 K
b0 G
bx000000000000000000000000000000000000000000000000000000000111111100000000000000000000000001111111000000000000000000000000011111110000000000000000000000000111111100000000000000000000000001111111 $
bx000000000000000000000000000000000000000000000000000000000111111100000000000000000000000001111111000000000000000000000000011111110000000000000000000000000111111100000000000000000000000001111111 H
b10 J
b0 I
b1 R
bx0000000000000000000000000000000000000000000000000000000001111111000000000000000000000000011111110000000000000000000000000111111100000000000000000000000000000000 "
bx0000000000000000000000000000000000000000000000000000000001111111000000000000000000000000011111110000000000000000000000000111111100000000000000000000000000000000 O
b10100000 P
1!
#48
0!
#52
b0 F
b10 L
b10 K
b0 G
b10 R
bx000000000000000000000000000000000000000000000000000000000000000000000000000000000000000001111111000000000000000000000000011111110000000000000000000000000111111100000000000000000000000000000000 "
bx000000000000000000000000000000000000000000000000000000000000000000000000000000000000000001111111000000000000000000000000011111110000000000000000000000000111111100000000000000000000000000000000 O
b11000000 P
bx00000000000000000000000000000000000000000000000000000000000000000000000000000000000000000111111100000000000000000000000001111111000000000000000000000000011111110000000000000000000000000111111100000000000000000000000001111111 $
bx00000000000000000000000000000000000000000000000000000000000000000000000000000000000000000111111100000000000000000000000001111111000000000000000000000000011111110000000000000000000000000111111100000000000000000000000001111111 H
b1 I
1!
#56
0!
#60
b0 F
b10 L
b10 K
b0 G
bx0000000000000000000000000000000000000000000000000000000000000000000000000000000000000000000000000000000000000000000000000111111100000000000000000000000001111111000000000000000000000000011111110000000000000000000000000111111100000000000000000000000001111111 $
bx0000000000000000000000000000000000000000000000000000000000000000000000000000000000000000000000000000000000000000000000000111111100000000000000000000000001111111000000000000000000000000011111110000000000000000000000000111111100000000000000000000000001111111 H
b10 I
b11 R
bx00000000000000000000000001111111000000000000000000000000000000000000000000000000000000000000000000000000000000000000000001111111000000000000000000000000011111110000000000000000000000000111111100000000000000000000000000000000 "
bx00000000000000000000000001111111000000000000000000000000000000000000000000000000000000000000000000000000000000000000000001111111000000000000000000000000011111110000000000000000000000000111111100000000000000000000000000000000 O
b11100000 P
1!
#64
0!
#68
b1111111 F
b10 L
b10 K
b1111111 G
b100 R
bx0000000000000000000000000111111100000000000000000000000001111111000000000000000000000000000000000000000000000000000000000000000000000000000000000000000001111111000000000000000000000000011111110000000000000000000000000111111100000000000000000000000000000000 "
bx0000000000000000000000000111111100000000000000000000000001111111000000000000000000000000000000000000000000000000000000000000000000000000000000000000000001111111000000000000000000000000011111110000000000000000000000000111111100000000000000000000000000000000 O
b100000000 P
b111111100000000000000000000000001111111000000000000000000000000011111110000000000000000000000000111111100000000000000000000000001111111 $
b111111100000000000000000000000001111111000000000000000000000000011111110000000000000000000000000111111100000000000000000000000001111111 H
b0 J
b0 I
1!
#72
0!
#76
b10 L
b10 K
b1 I
b10 Q
b0 R
bx000000000000000000000000011111110000000000000000000000000111111100000000000000000000000001111111000000000000000000000000000000000000000000000000000000000000000000000000000000000000000001111111000000000000000000000000011111110000000000000000000000000111111100000000000000000000000000000000 "
bx000000000000000000000000011111110000000000000000000000000111111100000000000000000000000001111111000000000000000000000000000000000000000000000000000000000000000000000000000000000000000001111111000000000000000000000000011111110000000000000000000000000111111100000000000000000000000000000000 O
b100100000 P
1!
#80
0!
#84
b0 F
b10 L
b10 K
b1111111 G
b1 R
bx00000000000000000000000001111111000000000000000000000000011111110000000000000000000000000111111100000000000000000000000001111111000000000000000000000000000000000000000000000000000000000000000000000000000000000000000001111111000000000000000000000000011111110000000000000000000000000111111100000000000000000000000000000000 "
bx00000000000000000000000001111111000000000000000000000000011111110000000000000000000000000111111100000000000000000000000001111111000000000000000000000000000000000000000000000000000000000000000000000000000000000000000001111111000000000000000000000000011111110000000000000000000000000111111100000000000000000000000000000000 O
b101000000 P
b10 I
1!
#88
0!
#92
b1111111 F
b10 L
b10 K
b1111111 G
b1 J
b0 I
b10 R
bx0000000000000000000000000000000000000000000000000000000001111111000000000000000000000000011111110000000000000000000000000111111100000000000000000000000001111111000000000000000000000000000000000000000000000000000000000000000000000000000000000000000001111111000000000000000000000000011111110000000000000000000000000111111100000000000000000000000000000000 "
bx0000000000000000000000000000000000000000000000000000000001111111000000000000000000000000011111110000000000000000000000000111111100000000000000000000000001111111000000000000000000000000000000000000000000000000000000000000000000000000000000000000000001111111000000000000000000000000011111110000000000000000000000000111111100000000000000000000000000000000 O
b101100000 P
1!
#96
0!
#100
b10 L
b10 K
b11 R
bx000000000000000000000000011111110000000000000000000000000000000000000000000000000000000001111111000000000000000000000000011111110000000000000000000000000111111100000000000000000000000001111111000000000000000000000000000000000000000000000000000000000000000000000000000000000000000001111111000000000000000000000000011111110000000000000000000000000111111100000000000000000000000000000000 "
bx000000000000000000000000011111110000000000000000000000000000000000000000000000000000000001111111000000000000000000000000011111110000000000000000000000000111111100000000000000000000000001111111000000000000000000000000000000000000000000000000000000000000000000000000000000000000000001111111000000000000000000000000011111110000000000000000000000000111111100000000000000000000000000000000 O
b110000000 P
b1 I
1!
#104
0!
#108
b0 F
b10 L
b10 K
b0 G
b10 I
b100 R
bx00000000000000000000000001111111000000000000000000000000011111110000000000000000000000000000000000000000000000000000000001111111000000000000000000000000011111110000000000000000000000000111111100000000000000000000000001111111000000000000000000000000000000000000000000000000000000000000000000000000000000000000000001111111000000000000000000000000011111110000000000000000000000000111111100000000000000000000000000000000 "
bx00000000000000000000000001111111000000000000000000000000011111110000000000000000000000000000000000000000000000000000000001111111000000000000000000000000011111110000000000000000000000000111111100000000000000000000000001111111000000000000000000000000000000000000000000000000000000000000000000000000000000000000000001111111000000000000000000000000011111110000000000000000000000000111111100000000000000000000000000000000 O
b110100000 P
1!
#112
0!
#116
b0 F
b10 L
b10 K
b0 G
b11 Q
b0 R
bx0000000000000000000000000111111100000000000000000000000001111111000000000000000000000000011111110000000000000000000000000000000000000000000000000000000001111111000000000000000000000000011111110000000000000000000000000111111100000000000000000000000001111111000000000000000000000000000000000000000000000000000000000000000000000000000000000000000001111111000000000000000000000000011111110000000000000000000000000111111100000000000000000000000000000000 "
bx0000000000000000000000000111111100000000000000000000000001111111000000000000000000000000011111110000000000000000000000000000000000000000000000000000000001111111000000000000000000000000011111110000000000000000000000000111111100000000000000000000000001111111000000000000000000000000000000000000000000000000000000000000000000000000000000000000000001111111000000000000000000000000011111110000000000000000000000000111111100000000000000000000000000000000 O
b111000000 P
b10 J
b0 I
1!
#120
0!
#124
b0 F
b10 L
b10 K
b0 G
b1 I
b1 R
bx000000000000000000000000000000000000000000000000000000000111111100000000000000000000000001111111000000000000000000000000011111110000000000000000000000000000000000000000000000000000000001111111000000000000000000000000011111110000000000000000000000000111111100000000000000000000000001111111000000000000000000000000000000000000000000000000000000000000000000000000000000000000000001111111000000000000000000000000011111110000000000000000000000000111111100000000000000000000000000000000 "
bx000000000000000000000000000000000000000000000000000000000111111100000000000000000000000001111111000000000000000000000000011111110000000000000000000000000000000000000000000000000000000001111111000000000000000000000000011111110000000000000000000000000111111100000000000000000000000001111111000000000000000000000000000000000000000000000000000000000000000000000000000000000000000001111111000000000000000000000000011111110000000000000000000000000111111100000000000000000000000000000000 O
b111100000 P
1!
#128
0!
#132
b0 F
b10 L
b10 K
b0 G
b10 R
bx00000000000000000000000000000000000000000000000000000000000000000000000000000000000000000111111100000000000000000000000001111111000000000000000000000000011111110000000000000000000000000000000000000000000000000000000001111111000000000000000000000000011111110000000000000000000000000111111100000000000000000000000001111111000000000000000000000000000000000000000000000000000000000000000000000000000000000000000001111111000000000000000000000000011111110000000000000000000000000111111100000000000000000000000000000000 "
bx00000000000000000000000000000000000000000000000000000000000000000000000000000000000000000111111100000000000000000000000001111111000000000000000000000000011111110000000000000000000000000000000000000000000000000000000001111111000000000000000000000000011111110000000000000000000000000111111100000000000000000000000001111111000000000000000000000000000000000000000000000000000000000000000000000000000000000000000001111111000000000000000000000000011111110000000000000000000000000111111100000000000000000000000000000000 O
b1000000000 P
b10 I
1!
#136
0!
#140
b1111111 F
b10 L
b10 K
b1111111 G
b0 J
b0 I
b11 R
bx0000000000000000000000000111111100000000000000000000000000000000000000000000000000000000000000000000000000000000000000000111111100000000000000000000000001111111000000000000000000000000011111110000000000000000000000000000000000000000000000000000000001111111000000000000000000000000011111110000000000000000000000000111111100000000000000000000000001111111000000000000000000000000000000000000000000000000000000000000000000000000000000000000000001111111000000000000000000000000011111110000000000000000000000000111111100000000000000000000000000000000 "
bx0000000000000000000000000111111100000000000000000000000000000000000000000000000000000000000000000000000000000000000000000111111100000000000000000000000001111111000000000000000000000000011111110000000000000000000000000000000000000000000000000000000001111111000000000000000000000000011111110000000000000000000000000111111100000000000000000000000001111111000000000000000000000000000000000000000000000000000000000000000000000000000000000000000001111111000000000000000000000000011111110000000000000000000000000111111100000000000000000000000000000000 O
b1000100000 P
1!
#144
0!
#148
b10 L
b10 K
b100 R
bx000000000000000000000000011111110000000000000000000000000111111100000000000000000000000000000000000000000000000000000000000000000000000000000000000000000111111100000000000000000000000001111111000000000000000000000000011111110000000000000000000000000000000000000000000000000000000001111111000000000000000000000000011111110000000000000000000000000111111100000000000000000000000001111111000000000000000000000000000000000000000000000000000000000000000000000000000000000000000001111111000000000000000000000000011111110000000000000000000000000111111100000000000000000000000000000000 "
bx000000000000000000000000011111110000000000000000000000000111111100000000000000000000000000000000000000000000000000000000000000000000000000000000000000000111111100000000000000000000000001111111000000000000000000000000011111110000000000000000000000000000000000000000000000000000000001111111000000000000000000000000011111110000000000000000000000000111111100000000000000000000000001111111000000000000000000000000000000000000000000000000000000000000000000000000000000000000000001111111000000000000000000000000011111110000000000000000000000000111111100000000000000000000000000000000 O
b1001000000 P
b1 I
1!
#152
0!
#156
b0 F
b10 L
b10 K
b1111111 G
b10 I
b100 Q
b0 R
bx00000000000000000000000001111111000000000000000000000000011111110000000000000000000000000111111100000000000000000000000000000000000000000000000000000000000000000000000000000000000000000111111100000000000000000000000001111111000000000000000000000000011111110000000000000000000000000000000000000000000000000000000001111111000000000000000000000000011111110000000000000000000000000111111100000000000000000000000001111111000000000000000000000000000000000000000000000000000000000000000000000000000000000000000001111111000000000000000000000000011111110000000000000000000000000111111100000000000000000000000000000000 "
bx00000000000000000000000001111111000000000000000000000000011111110000000000000000000000000111111100000000000000000000000000000000000000000000000000000000000000000000000000000000000000000111111100000000000000000000000001111111000000000000000000000000011111110000000000000000000000000000000000000000000000000000000001111111000000000000000000000000011111110000000000000000000000000111111100000000000000000000000001111111000000000000000000000000000000000000000000000000000000000000000000000000000000000000000001111111000000000000000000000000011111110000000000000000000000000111111100000000000000000000000000000000 O
b1001100000 P
1!
#160
0!
#164
b1111111 F
b10 L
b10 K
b1111111 G
b1 R
bx0000000000000000000000000000000000000000000000000000000001111111000000000000000000000000011111110000000000000000000000000111111100000000000000000000000000000000000000000000000000000000000000000000000000000000000000000111111100000000000000000000000001111111000000000000000000000000011111110000000000000000000000000000000000000000000000000000000001111111000000000000000000000000011111110000000000000000000000000111111100000000000000000000000001111111000000000000000000000000000000000000000000000000000000000000000000000000000000000000000001111111000000000000000000000000011111110000000000000000000000000111111100000000000000000000000000000000 "
bx0000000000000000000000000000000000000000000000000000000001111111000000000000000000000000011111110000000000000000000000000111111100000000000000000000000000000000000000000000000000000000000000000000000000000000000000000111111100000000000000000000000001111111000000000000000000000000011111110000000000000000000000000000000000000000000000000000000001111111000000000000000000000000011111110000000000000000000000000111111100000000000000000000000001111111000000000000000000000000000000000000000000000000000000000000000000000000000000000000000001111111000000000000000000000000011111110000000000000000000000000111111100000000000000000000000000000000 O
b1010000000 P
b1 J
b0 I
1!
#168
0!
#172
b10 L
b10 K
b1 I
b10 R
bx000000000000000000000000000000000000000000000000000000000000000000000000000000000000000001111111000000000000000000000000011111110000000000000000000000000111111100000000000000000000000000000000000000000000000000000000000000000000000000000000000000000111111100000000000000000000000001111111000000000000000000000000011111110000000000000000000000000000000000000000000000000000000001111111000000000000000000000000011111110000000000000000000000000111111100000000000000000000000001111111000000000000000000000000000000000000000000000000000000000000000000000000000000000000000001111111000000000000000000000000011111110000000000000000000000000111111100000000000000000000000000000000 "
bx000000000000000000000000000000000000000000000000000000000000000000000000000000000000000001111111000000000000000000000000011111110000000000000000000000000111111100000000000000000000000000000000000000000000000000000000000000000000000000000000000000000111111100000000000000000000000001111111000000000000000000000000011111110000000000000000000000000000000000000000000000000000000001111111000000000000000000000000011111110000000000000000000000000111111100000000000000000000000001111111000000000000000000000000000000000000000000000000000000000000000000000000000000000000000001111111000000000000000000000000011111110000000000000000000000000111111100000000000000000000000000000000 O
b1010100000 P
1!
#176
0!
#180
b0 F
b10 L
b10 K
b0 G
b11 R
bx00000000000000000000000000000000000000000000000000000000000000000000000000000000000000000000000000000000000000000000000001111111000000000000000000000000011111110000000000000000000000000111111100000000000000000000000000000000000000000000000000000000000000000000000000000000000000000111111100000000000000000000000001111111000000000000000000000000011111110000000000000000000000000000000000000000000000000000000001111111000000000000000000000000011111110000000000000000000000000111111100000000000000000000000001111111000000000000000000000000000000000000000000000000000000000000000000000000000000000000000001111111000000000000000000000000011111110000000000000000000000000111111100000000000000000000000000000000 "
bx00000000000000000000000000000000000000000000000000000000000000000000000000000000000000000000000000000000000000000000000001111111000000000000000000000000011111110000000000000000000000000111111100000000000000000000000000000000000000000000000000000000000000000000000000000000000000000111111100000000000000000000000001111111000000000000000000000000011111110000000000000000000000000000000000000000000000000000000001111111000000000000000000000000011111110000000000000000000000000111111100000000000000000000000001111111000000000000000000000000000000000000000000000000000000000000000000000000000000000000000001111111000000000000000000000000011111110000000000000000000000000111111100000000000000000000000000000000 O
b1011000000 P
b10 I
1!
#184
0!
#188
b0 F
b10 L
b10 K
b0 G
b10 J
b0 I
b100 R
bx0000000000000000000000000000000000000000000000000000000000000000000000000000000000000000000000000000000000000000000000000000000000000000000000000000000001111111000000000000000000000000011111110000000000000000000000000111111100000000000000000000000000000000000000000000000000000000000000000000000000000000000000000111111100000000000000000000000001111111000000000000000000000000011111110000000000000000000000000000000000000000000000000000000001111111000000000000000000000000011111110000000000000000000000000111111100000000000000000000000001111111000000000000000000000000000000000000000000000000000000000000000000000000000000000000000001111111000000000000000000000000011111110000000000000000000000000111111100000000000000000000000000000000 "
bx0000000000000000000000000000000000000000000000000000000000000000000000000000000000000000000000000000000000000000000000000000000000000000000000000000000001111111000000000000000000000000011111110000000000000000000000000111111100000000000000000000000000000000000000000000000000000000000000000000000000000000000000000111111100000000000000000000000001111111000000000000000000000000011111110000000000000000000000000000000000000000000000000000000001111111000000000000000000000000011111110000000000000000000000000111111100000000000000000000000001111111000000000000000000000000000000000000000000000000000000000000000000000000000000000000000001111111000000000000000000000000011111110000000000000000000000000111111100000000000000000000000000000000 O
b1011100000 P
1!
#192
0!
#196
b0 F
b10 L
b10 K
b0 G
b0 R
b0 Q
bx000000000000000000000000000000000000000000000000000000000000000000000000000000000000000000000000000000000000000000000000000000000000000000000000000000000000000000000000000000000000000001111111000000000000000000000000011111110000000000000000000000000111111100000000000000000000000000000000000000000000000000000000000000000000000000000000000000000111111100000000000000000000000001111111000000000000000000000000011111110000000000000000000000000000000000000000000000000000000001111111000000000000000000000000011111110000000000000000000000000111111100000000000000000000000001111111000000000000000000000000000000000000000000000000000000000000000000000000000000000000000001111111000000000000000000000000011111110000000000000000000000000111111100000000000000000000000000000000 "
bx000000000000000000000000000000000000000000000000000000000000000000000000000000000000000000000000000000000000000000000000000000000000000000000000000000000000000000000000000000000000000001111111000000000000000000000000011111110000000000000000000000000111111100000000000000000000000000000000000000000000000000000000000000000000000000000000000000000111111100000000000000000000000001111111000000000000000000000000011111110000000000000000000000000000000000000000000000000000000001111111000000000000000000000000011111110000000000000000000000000111111100000000000000000000000001111111000000000000000000000000000000000000000000000000000000000000000000000000000000000000000001111111000000000000000000000000011111110000000000000000000000000111111100000000000000000000000000000000 O
b1100000000 P
b1 I
1!
#200
0!
